{
  "trainId": "1104",
  "capturedAt": "2026-07-04T23:44:59.061Z",
  "data": [
    {
      "train_id": "1104",
      "ka_name": "COMMUTER LINE BOGOR",
      "station_id": "DP",
      "station_name": "DEPOK",
      "time_est": "03:50:00",
      "transit_station": false,
      "color": "#E30A16",
      "transit": ""
    },
    {
      "train_id": "1104",
      "ka_name": "COMMUTER LINE BOGOR",
      "station_id": "CTA",
      "station_name": "CITAYAM",
      "time_est": "03:57:00",
      "transit_station": true,
      "color": "#E30A16",
      "transit": ""
    },
    {
      "train_id": "1104",
      "ka_name": "COMMUTER LINE BOGOR",
      "station_id": "BJD",
      "station_name": "BOJONGGEDE",
      "time_est": "04:03:00",
      "transit_station": false,
      "color": "#E30A16",
      "transit": ""
    },
    {
      "train_id": "1104",
      "ka_name": "COMMUTER LINE BOGOR",
      "station_id": "CLT",
      "station_name": "CILEBUT",
      "time_est": "04:09:00",
      "transit_station": false,
      "color": "#E30A16",
      "transit": ""
    },
    {
      "train_id": "1104",
      "ka_name": "COMMUTER LINE BOGOR",
      "station_id": "BOO",
      "station_name": "BOGOR",
      "time_est": "04:17:00",
      "transit_station": false,
      "color": "#E30A16",
      "transit": ""
    }
  ]
}
